README.md
setup.py
terminalmagic/__init__.py
terminalmagic.egg-info/PKG-INFO
terminalmagic.egg-info/SOURCES.txt
terminalmagic.egg-info/dependency_links.txt
terminalmagic.egg-info/not-zip-safe
terminalmagic.egg-info/top_level.txt