Metadata-Version: 1.0
Name: terminalmagic
Version: 0.4
Summary: Convenience functions for using the terminal in ways you didn't know were possible.
Home-page: https://github.com/maveobi/terminalmagic
Author: maveobi
Author-email: nospam@example.com
License: MIT
Platform: UNKNOWN
